trading_gym_next/__init__.py
trading_gym_next/env.py
trading_gym_next-1.0.3.dist-info/METADATA
trading_gym_next-1.0.3.dist-info/WHEEL
trading_gym_next-1.0.3.dist-info/top_level.txt
trading_gym_next-1.0.3.dist-info/RECORD
