Metadata-Version: 2.1
Name: trading-gym-next
Version: 1.0.3
Summary: Trading Gym with Backtesting.py
Home-page: UNKNOWN
Author: Rui Hirano
Author-email: UNKNOWN
License: MIT
Platform: UNKNOWN
Requires-Dist: gym
Requires-Dist: backtesting
Requires-Dist: pandas
Requires-Dist: numpy
